SerialLibrary.py
robotframework_pyserial-1.4.0.dist-info/LICENSE
robotframework_pyserial-1.4.0.dist-info/METADATA
robotframework_pyserial-1.4.0.dist-info/WHEEL
robotframework_pyserial-1.4.0.dist-info/top_level.txt
robotframework_pyserial-1.4.0.dist-info/RECORD
