Metadata-Version: 2.1
Name: robotframework-pyserial
Version: 1.4.0
Summary: Robotframework implementation of beloved pyserial module
Home-page: https://reharish.github.io/cv
Author: reharish
Author-email: rengarajharish@gmail.com
License: Apache License 2.0
License-File: LICENSE
Requires-Dist: robotframework
Requires-Dist: pyserial
